{
  "space_group_number": 114,
  "ebr_data": {
    "irreps": [
      "A1A4",
      "\u03931(1)\u00a0\u2295\u00a0\u03934",
      "M5",
      "Z5",
      "R1",
      "X1",
      "\u039b1(1)\u00a0\u2295\u00a0\u039b2",
      "V1V2",
      "C1(1)\u00a0\u2295\u00a0C2",
      "\u03941(1)\u00a0\u2295\u00a0\u03942",
      "S1S2",
      "\u03a31(1)\u00a0\u2295\u00a0\u03a32",
      "T1T2",
      "U1(1)\u00a0\u2295\u00a0U2",
      "W1W2",
      "Y1Y2",
      "2\u00a0B1",
      "2\u00a0D1",
      "2\u00a0E1",
      "F1F1",
      "2\u00a0GP1",
      "A2A3",
      "\u03932(1)\u00a0\u2295\u00a0\u03933",
      "A5A5",
      "2\u00a0\u03935",
      "M1M3(2)\u00a0\u2295\u00a0M2M4",
      "Z1Z2(2)\u00a0\u2295\u00a0Z3Z4",
      "2\u00a0R1",
      "2\u00a0X1",
      "2\u00a0\u039b3\u039b4",
      "V3V3(2)\u00a0\u2295\u00a0V4V4",
      "2\u00a0C1(1)\u00a0\u2295\u00a02\u00a0C2",
      "2\u00a0\u03941(1)\u00a0\u2295\u00a02\u00a0\u03942",
      "2\u00a0S1S2",
      "2\u00a0\u03a31(1)\u00a0\u2295\u00a02\u00a0\u03a32",
      "2\u00a0T1T2",
      "2\u00a0U1(1)\u00a0\u2295\u00a02\u00a0U2",
      "2\u00a0W1W2",
      "2\u00a0Y1Y2",
      "4\u00a0B1",
      "4\u00a0D1",
      "4\u00a0E1",
      "2\u00a0F1F1",
      "4\u00a0GP1",
      "\u03931(1)\u00a0\u2295\u00a0\u03932(1)\u00a0\u2295\u00a0\u03933(1)\u00a0\u2295\u00a0\u03934",
      "2\u00a0Z5",
      "2\u00a0\u039b1(1)\u00a0\u2295\u00a02\u00a0\u039b2",
      "A1A4(2)\u00a0\u2295\u00a0A2A3",
      "2\u00a0M5",
      "2\u00a0V1V2",
      "A7A7",
      "2\u03937",
      "M6M7",
      "Z6Z7",
      "R2R5(2)\u00a0\u2295R3R4",
      "X2X5(2)\u00a0\u2295X3X4",
      "2\u039b5",
      "V5V5",
      "2C3(1)\u00a0\u2295\u00a02C4",
      "2\u03943(1)\u00a0\u2295\u00a02\u03944",
      "2S3S4",
      "2\u03a33(1)\u00a0\u2295\u00a02\u03a34",
      "2T3T4",
      "2U3(1)\u00a0\u2295\u00a02U4",
      "2W3W4",
      "2Y3Y4",
      "4B2",
      "4D2",
      "4E2",
      "2F2F2",
      "4GP2",
      "A6A6",
      "2\u03936",
      "A6A6(4)\u00a0\u2295A7A7",
      "2\u03936(2)\u00a0\u2295\u00a02\u03937",
      "2M6M7",
      "2Z6Z7",
      "2R2R5(2)\u00a0\u2295\u00a02R3R4",
      "2X2X5(2)\u00a0\u2295\u00a02X3X4",
      "4\u039b5",
      "2V5V5",
      "4C3(1)\u00a0\u2295\u00a04C4",
      "4\u03943(1)\u00a0\u2295\u00a04\u03944",
      "4S3S4",
      "4\u03a33(1)\u00a0\u2295\u00a04\u03a34",
      "4T3T4",
      "4U3(1)\u00a0\u2295\u00a04U4",
      "4W3W4",
      "4Y3Y4",
      "8B2",
      "8D2",
      "8E2",
      "4F2F2",
      "8GP2"
    ],
    "irrep_multiplicities": {
      "4\u00a0D1": 4,
      "2\u00a0C1(1)\u00a0\u2295\u00a02\u00a0C2": 4,
      "2\u00a0S1S2": 4,
      "2\u00a0\u03a31(1)\u00a0\u2295\u00a02\u00a0\u03a32": 4,
      "2\u00a0T1T2": 4,
      "2\u00a0U1(1)\u00a0\u2295\u00a02\u00a0U2": 4,
      "2\u00a0W1W2": 4,
      "2\u00a0Y1Y2": 4,
      "4\u00a0B1": 4,
      "4GP2": 4,
      "4\u00a0E1": 4,
      "2\u00a0F1F1": 4,
      "4\u00a0GP1": 4,
      "2F2F2": 4,
      "4E2": 4,
      "4D2": 4,
      "4B2": 4,
      "2Y3Y4": 4,
      "2W3W4": 4,
      "2U3(1)\u00a0\u2295\u00a02U4": 4,
      "2T3T4": 4,
      "M6M7": 4,
      "Z6Z7": 4,
      "R2R5(2)\u00a0\u2295R3R4": 4,
      "X2X5(2)\u00a0\u2295X3X4": 4,
      "2\u039b5": 4,
      "V5V5": 4,
      "2C3(1)\u00a0\u2295\u00a02C4": 4,
      "2\u03943(1)\u00a0\u2295\u00a02\u03944": 4,
      "2\u00a0\u03941(1)\u00a0\u2295\u00a02\u00a0\u03942": 4,
      "2S3S4": 4,
      "2\u03a33(1)\u00a0\u2295\u00a02\u03a34": 4,
      "W1W2": 4,
      "M5": 4,
      "Z5": 4,
      "R1": 4,
      "X1": 4,
      "\u039b1(1)\u00a0\u2295\u00a0\u039b2": 4,
      "V1V2": 4,
      "C1(1)\u00a0\u2295\u00a0C2": 4,
      "\u03941(1)\u00a0\u2295\u00a0\u03942": 4,
      "S1S2": 4,
      "\u03a31(1)\u00a0\u2295\u00a0\u03a32": 4,
      "T1T2": 4,
      "U1(1)\u00a0\u2295\u00a0U2": 4,
      "Y1Y2": 4,
      "2\u00a0B1": 4,
      "2\u00a0D1": 4,
      "2\u00a0E1": 4,
      "F1F1": 4,
      "2\u00a0GP1": 4,
      "2\u00a0R1": 4,
      "2\u00a0X1": 4,
      "4C3(1)\u00a0\u2295\u00a04C4": 3,
      "2X2X5(2)\u00a0\u2295\u00a02X3X4": 3,
      "2R2R5(2)\u00a0\u2295\u00a02R3R4": 3,
      "2Z6Z7": 3,
      "2M6M7": 3,
      "2\u03936(2)\u00a0\u2295\u00a02\u03937": 3,
      "A6A6(4)\u00a0\u2295A7A7": 3,
      "4\u03943(1)\u00a0\u2295\u00a04\u03944": 3,
      "8GP2": 3,
      "4S3S4": 3,
      "4\u03a33(1)\u00a0\u2295\u00a04\u03a34": 3,
      "4F2F2": 3,
      "8E2": 3,
      "A5A5": 3,
      "2\u00a0\u03935": 3,
      "M1M3(2)\u00a0\u2295\u00a0M2M4": 3,
      "Z1Z2(2)\u00a0\u2295\u00a0Z3Z4": 3,
      "2\u00a0\u039b3\u039b4": 3,
      "V3V3(2)\u00a0\u2295\u00a0V4V4": 3,
      "2V5V5": 3,
      "8D2": 3,
      "8B2": 3,
      "4Y3Y4": 3,
      "4W3W4": 3,
      "4U3(1)\u00a0\u2295\u00a04U4": 3,
      "4T3T4": 3,
      "4\u039b5": 3,
      "A1A4": 2,
      "2\u03936": 2,
      "A6A6": 2,
      "2\u03937": 2,
      "A7A7": 2,
      "\u03931(1)\u00a0\u2295\u00a0\u03934": 2,
      "\u03932(1)\u00a0\u2295\u00a0\u03933": 2,
      "A2A3": 2,
      "2\u00a0V1V2": 1,
      "2\u00a0M5": 1,
      "2\u00a0\u039b1(1)\u00a0\u2295\u00a02\u00a0\u039b2": 1,
      "2\u00a0Z5": 1,
      "\u03931(1)\u00a0\u2295\u00a0\u03932(1)\u00a0\u2295\u00a0\u03933(1)\u00a0\u2295\u00a0\u03934": 1,
      "A1A4(2)\u00a0\u2295\u00a0A2A3": 1
    },
    "branch1_irreps": [
      "M6M7,Z6Z7,A6A6,R2R5,R3R4,X2X5,X3X4,\u03936,\u03936",
      "M6M7,Z6Z7,A6A6,R2R5,R3R4,X2X5,X3X4,\u03936,\u03937",
      "M6M7,Z6Z7,A6A6,R2R5,R3R4,X2X5,X3X4,\u03937,\u03937",
      "M6M7,Z6Z7,A6A6,R2R5,R3R4,X2X5,X3X4,\u03936,\u03936",
      "M6M7,Z6Z7,A6A6,R2R5,R3R4,X2X5,X3X4,\u03936,\u03937",
      "M6M7,Z6Z7,A6A6,R2R5,R3R4,X2X5,X3X4,\u03937,\u03937",
      "M6M7,Z6Z7,A6A6,R2R5,R3R4,X2X5,X3X4,\u03936,\u03936",
      "M6M7,Z6Z7,A6A6,R2R5,R3R4,X2X5,X3X4,\u03936,\u03937",
      "M6M7,Z6Z7,A6A6,R2R5,R3R4,X2X5,X3X4,\u03937,\u03937",
      "M6M7,Z6Z7,A6A6,R2R5,R3R4,X2X5,X3X4,\u03936,\u03936",
      "M6M7,Z6Z7,A6A6,R2R5,R3R4,X2X5,X3X4,\u03936,\u03937",
      "M6M7,Z6Z7,A6A6,R2R5,R3R4,X2X5,X3X4,\u03937,\u03937",
      "M6M7,Z6Z7,A6A6,R2R5,R3R4,X2X5,X3X4,\u03936,\u03936",
      "M6M7,Z6Z7,A6A6,R2R5,R3R4,X2X5,X3X4,\u03936,\u03937",
      "M6M7,Z6Z7,A6A6,R2R5,R3R4,X2X5,X3X4,\u03937,\u03937",
      "M6M7,Z6Z7,A6A6,R2R5,R3R4,X2X5,X3X4,\u03936,\u03936",
      "M6M7,Z6Z7,A6A6,R2R5,R3R4,X2X5,X3X4,\u03936,\u03937",
      "M6M7,Z6Z7,A6A6,R2R5,R3R4,X2X5,X3X4,\u03937,\u03937",
      "M6M7,Z6Z7,A6A6,R2R5,R3R4,X2X5,X3X4,\u03936,\u03936",
      "M6M7,Z6Z7,A6A6,R2R5,R3R4,X2X5,X3X4,\u03936,\u03937",
      "M6M7,Z6Z7,A6A6,R2R5,R3R4,X2X5,X3X4,\u03937,\u03937",
      "M6M7,Z6Z7,A6A6,R2R5,R3R4,X2X5,X3X4,\u03936,\u03936",
      "M6M7,Z6Z7,A6A6,R2R5,R3R4,X2X5,X3X4,\u03936,\u03937",
      "M6M7,Z6Z7,A6A6,R2R5,R3R4,X2X5,X3X4,\u03937,\u03937",
      "M6M7,Z6Z7,A6A6,R2R5,R3R4,X2X5,X3X4,\u03936,\u03936",
      "M6M7,Z6Z7,A6A6,R2R5,R3R4,X2X5,X3X4,\u03936,\u03937",
      "M6M7,Z6Z7,A6A6,R2R5,R3R4,X2X5,X3X4,\u03937,\u03937",
      "M6M7,Z6Z7,A6A6,R2R5,R3R4,X2X5,X3X4,\u03936,\u03936",
      "M6M7,Z6Z7,A6A6,R2R5,R3R4,X2X5,X3X4,\u03936,\u03937",
      "M6M7,Z6Z7,A6A6,R2R5,R3R4,X2X5,X3X4,\u03937,\u03937",
      "M6M7,Z6Z7,A6A6,R2R5,R3R4,X2X5,X3X4,\u03936,\u03936",
      "M6M7,Z6Z7,A6A6,R2R5,R3R4,X2X5,X3X4,\u03936,\u03937",
      "M6M7,Z6Z7,A6A6,R2R5,R3R4,X2X5,X3X4,\u03937,\u03937",
      "M6M7,Z6Z7,A6A6,R2R5,R3R4,X2X5,X3X4,\u03936,\u03936",
      "M6M7,Z6Z7,A6A6,R2R5,R3R4,X2X5,X3X4,\u03936,\u03937",
      "M6M7,Z6Z7,A6A6,R2R5,R3R4,X2X5,X3X4,\u03937,\u03937",
      "M6M7,Z6Z7,A6A6,R2R5,R3R4,X2X5,X3X4,\u03936,\u03936",
      "M6M7,Z6Z7,A6A6,R2R5,R3R4,X2X5,X3X4,\u03936,\u03937",
      "M6M7,Z6Z7,A6A6,R2R5,R3R4,X2X5,X3X4,\u03937,\u03937",
      "M6M7,Z6Z7,A6A6,R2R5,R3R4,X2X5,X3X4,\u03936,\u03936",
      "M6M7,Z6Z7,A6A6,R2R5,R3R4,X2X5,X3X4,\u03936,\u03937",
      "M6M7,Z6Z7,A6A6,R2R5,R3R4,X2X5,X3X4,\u03937,\u03937",
      "M6M7,Z6Z7,A6A6,R2R5,R3R4,X2X5,X3X4,\u03936,\u03936",
      "M6M7,Z6Z7,A6A6,R2R5,R3R4,X2X5,X3X4,\u03936,\u03937",
      "M6M7,Z6Z7,A6A6,R2R5,R3R4,X2X5,X3X4,\u03937,\u03937",
      "M6M7,Z6Z7,A6A6,R2R5,R3R4,X2X5,X3X4,\u03936,\u03936",
      "M6M7,Z6Z7,A6A6,R2R5,R3R4,X2X5,X3X4,\u03936,\u03937",
      "M6M7,Z6Z7,A6A6,R2R5,R3R4,X2X5,X3X4,\u03937,\u03937",
      "M6M7,Z6Z7,A6A6,R2R5,R3R4,X2X5,X3X4,\u03936,\u03936",
      "M6M7,Z6Z7,A6A6,R2R5,R3R4,X2X5,X3X4,\u03936,\u03937",
      "M6M7,Z6Z7,A6A6,R2R5,R3R4,X2X5,X3X4,\u03937,\u03937",
      "M6M7,Z6Z7,A6A6,R2R5,R3R4,X2X5,X3X4,\u03936,\u03936",
      "M6M7,Z6Z7,A6A6,R2R5,R3R4,X2X5,X3X4,\u03936,\u03937",
      "M6M7,Z6Z7,A6A6,R2R5,R3R4,X2X5,X3X4,\u03937,\u03937",
      "M6M7,Z6Z7,A6A6,R2R5,R3R4,X2X5,X3X4,\u03936,\u03936",
      "M6M7,Z6Z7,A6A6,R2R5,R3R4,X2X5,X3X4,\u03936,\u03937",
      "M6M7,Z6Z7,A6A6,R2R5,R3R4,X2X5,X3X4,\u03937,\u03937",
      "M6M7,Z6Z7,A6A6,R2R5,R3R4,X2X5,X3X4,\u03936,\u03936",
      "M6M7,Z6Z7,A6A6,R2R5,R3R4,X2X5,X3X4,\u03936,\u03937",
      "M6M7,Z6Z7,A6A6,R2R5,R3R4,X2X5,X3X4,\u03937,\u03937",
      "M6M7,Z6Z7,A6A6,R2R5,R3R4,X2X5,X3X4,\u03936,\u03936",
      "M6M7,Z6Z7,A6A6,R2R5,R3R4,X2X5,X3X4,\u03936,\u03937",
      "M6M7,Z6Z7,A6A6,R2R5,R3R4,X2X5,X3X4,\u03937,\u03937"
    ],
    "branch2_irreps": [
      "M6M7,Z6Z7,A7A7,R2R5,R3R4,X2X5,X3X4,\u03937,\u03937",
      "M6M7,Z6Z7,A7A7,R2R5,R3R4,X2X5,X3X4,\u03936,\u03937",
      "M6M7,Z6Z7,A7A7,R2R5,R3R4,X2X5,X3X4,\u03936,\u03936",
      "M6M7,Z6Z7,A7A7,R2R5,R3R4,X2X5,X3X4,\u03937,\u03937",
      "M6M7,Z6Z7,A7A7,R2R5,R3R4,X2X5,X3X4,\u03936,\u03937",
      "M6M7,Z6Z7,A7A7,R2R5,R3R4,X2X5,X3X4,\u03936,\u03936",
      "M6M7,Z6Z7,A7A7,R2R5,R3R4,X2X5,X3X4,\u03937,\u03937",
      "M6M7,Z6Z7,A7A7,R2R5,R3R4,X2X5,X3X4,\u03936,\u03937",
      "M6M7,Z6Z7,A7A7,R2R5,R3R4,X2X5,X3X4,\u03936,\u03936",
      "M6M7,Z6Z7,A7A7,R2R5,R3R4,X2X5,X3X4,\u03937,\u03937",
      "M6M7,Z6Z7,A7A7,R2R5,R3R4,X2X5,X3X4,\u03936,\u03937",
      "M6M7,Z6Z7,A7A7,R2R5,R3R4,X2X5,X3X4,\u03936,\u03936",
      "M6M7,Z6Z7,A7A7,R2R5,R3R4,X2X5,X3X4,\u03937,\u03937",
      "M6M7,Z6Z7,A7A7,R2R5,R3R4,X2X5,X3X4,\u03936,\u03937",
      "M6M7,Z6Z7,A7A7,R2R5,R3R4,X2X5,X3X4,\u03936,\u03936",
      "M6M7,Z6Z7,A7A7,R2R5,R3R4,X2X5,X3X4,\u03937,\u03937",
      "M6M7,Z6Z7,A7A7,R2R5,R3R4,X2X5,X3X4,\u03936,\u03937",
      "M6M7,Z6Z7,A7A7,R2R5,R3R4,X2X5,X3X4,\u03936,\u03936",
      "M6M7,Z6Z7,A7A7,R2R5,R3R4,X2X5,X3X4,\u03937,\u03937",
      "M6M7,Z6Z7,A7A7,R2R5,R3R4,X2X5,X3X4,\u03936,\u03937",
      "M6M7,Z6Z7,A7A7,R2R5,R3R4,X2X5,X3X4,\u03936,\u03936",
      "M6M7,Z6Z7,A7A7,R2R5,R3R4,X2X5,X3X4,\u03937,\u03937",
      "M6M7,Z6Z7,A7A7,R2R5,R3R4,X2X5,X3X4,\u03936,\u03937",
      "M6M7,Z6Z7,A7A7,R2R5,R3R4,X2X5,X3X4,\u03936,\u03936",
      "M6M7,Z6Z7,A7A7,R2R5,R3R4,X2X5,X3X4,\u03937,\u03937",
      "M6M7,Z6Z7,A7A7,R2R5,R3R4,X2X5,X3X4,\u03936,\u03937",
      "M6M7,Z6Z7,A7A7,R2R5,R3R4,X2X5,X3X4,\u03936,\u03936",
      "M6M7,Z6Z7,A7A7,R2R5,R3R4,X2X5,X3X4,\u03937,\u03937",
      "M6M7,Z6Z7,A7A7,R2R5,R3R4,X2X5,X3X4,\u03936,\u03937",
      "M6M7,Z6Z7,A7A7,R2R5,R3R4,X2X5,X3X4,\u03936,\u03936",
      "M6M7,Z6Z7,A7A7,R2R5,R3R4,X2X5,X3X4,\u03937,\u03937",
      "M6M7,Z6Z7,A7A7,R2R5,R3R4,X2X5,X3X4,\u03936,\u03937",
      "M6M7,Z6Z7,A7A7,R2R5,R3R4,X2X5,X3X4,\u03936,\u03936",
      "M6M7,Z6Z7,A7A7,R2R5,R3R4,X2X5,X3X4,\u03937,\u03937",
      "M6M7,Z6Z7,A7A7,R2R5,R3R4,X2X5,X3X4,\u03936,\u03937",
      "M6M7,Z6Z7,A7A7,R2R5,R3R4,X2X5,X3X4,\u03936,\u03936",
      "M6M7,Z6Z7,A7A7,R2R5,R3R4,X2X5,X3X4,\u03937,\u03937",
      "M6M7,Z6Z7,A7A7,R2R5,R3R4,X2X5,X3X4,\u03936,\u03937",
      "M6M7,Z6Z7,A7A7,R2R5,R3R4,X2X5,X3X4,\u03936,\u03936",
      "M6M7,Z6Z7,A7A7,R2R5,R3R4,X2X5,X3X4,\u03937,\u03937",
      "M6M7,Z6Z7,A7A7,R2R5,R3R4,X2X5,X3X4,\u03936,\u03937",
      "M6M7,Z6Z7,A7A7,R2R5,R3R4,X2X5,X3X4,\u03936,\u03936",
      "M6M7,Z6Z7,A7A7,R2R5,R3R4,X2X5,X3X4,\u03937,\u03937",
      "M6M7,Z6Z7,A7A7,R2R5,R3R4,X2X5,X3X4,\u03936,\u03937",
      "M6M7,Z6Z7,A7A7,R2R5,R3R4,X2X5,X3X4,\u03936,\u03936",
      "M6M7,Z6Z7,A7A7,R2R5,R3R4,X2X5,X3X4,\u03937,\u03937",
      "M6M7,Z6Z7,A7A7,R2R5,R3R4,X2X5,X3X4,\u03936,\u03937",
      "M6M7,Z6Z7,A7A7,R2R5,R3R4,X2X5,X3X4,\u03936,\u03936",
      "M6M7,Z6Z7,A7A7,R2R5,R3R4,X2X5,X3X4,\u03937,\u03937",
      "M6M7,Z6Z7,A7A7,R2R5,R3R4,X2X5,X3X4,\u03936,\u03937",
      "M6M7,Z6Z7,A7A7,R2R5,R3R4,X2X5,X3X4,\u03936,\u03936",
      "M6M7,Z6Z7,A7A7,R2R5,R3R4,X2X5,X3X4,\u03937,\u03937",
      "M6M7,Z6Z7,A7A7,R2R5,R3R4,X2X5,X3X4,\u03936,\u03937",
      "M6M7,Z6Z7,A7A7,R2R5,R3R4,X2X5,X3X4,\u03936,\u03936",
      "M6M7,Z6Z7,A7A7,R2R5,R3R4,X2X5,X3X4,\u03937,\u03937",
      "M6M7,Z6Z7,A7A7,R2R5,R3R4,X2X5,X3X4,\u03936,\u03937",
      "M6M7,Z6Z7,A7A7,R2R5,R3R4,X2X5,X3X4,\u03936,\u03936",
      "M6M7,Z6Z7,A7A7,R2R5,R3R4,X2X5,X3X4,\u03937,\u03937",
      "M6M7,Z6Z7,A7A7,R2R5,R3R4,X2X5,X3X4,\u03936,\u03937",
      "M6M7,Z6Z7,A7A7,R2R5,R3R4,X2X5,X3X4,\u03936,\u03936",
      "M6M7,Z6Z7,A7A7,R2R5,R3R4,X2X5,X3X4,\u03937,\u03937",
      "M6M7,Z6Z7,A7A7,R2R5,R3R4,X2X5,X3X4,\u03936,\u03937",
      "M6M7,Z6Z7,A7A7,R2R5,R3R4,X2X5,X3X4,\u03936,\u03936"
    ]
  },
  "topological_indices": {},
  "decomposition_branches": {
    "decomposition_indices": [
      1.0,
      2.0,
      3.0
    ]
  },
  "graph_info": {
    "num_nodes": 21,
    "num_edges": 742,
    "node_feature_dim": 10
  }
}